{
  "classname": null,
  "name": null,
  "animation": {
    "classname": null,
    "name": "AnimationManager",
    "actionlist": []
  },
  "dataScale": 1,
  "designHeight": 192,
  "designWidth": 153,
  "textures": [],
  "texturesPng": [],
  "version": "1.6.0.0",
  "widgetTree": {
    "classname": "Panel",
    "name": null,
    "children": [
      {
        "classname": "Button",
        "name": null,
        "children": [
          {
            "classname": "ImageView",
            "name": null,
            "children": [],
            "options": {
              "__type": "ImageViewSurrogate:#EditorCommon.JsonModel.Component.GUI",
              "classname": "ImageView",
              "name": "Image_daoju",
              "ZOrder": 0,
              "actiontag": 66167408,
              "anchorPointX": 0.5,
              "anchorPointY": 0.5,
              "classType": "CocoStudio.EngineAdapterWrap.CSImageView",
              "colorB": 255,
              "colorG": 255,
              "colorR": 255,
              "customProperty": "",
              "flipX": false,
              "flipY": false,
              "height": 70,
              "ignoreSize": true,
              "layoutParameter": null,
              "opacity": 255,
              "positionPercentX": 0,
              "positionPercentY": 0.03125,
              "positionType": 0,
              "rotation": 0,
              "scaleX": 1,
              "scaleY": 1,
              "sizePercentX": 0.503268,
              "sizePercentY": 0.364583343,
              "sizeType": 0,
              "tag": 99,
              "touchAble": false,
              "useMergedTexture": false,
              "visible": true,
              "width": 77,
              "x": 0,
              "y": 6,
              "capInsetsHeight": 1,
              "capInsetsWidth": 1,
              "capInsetsX": 0,
              "capInsetsY": 0,
              "fileName": null,
              "fileNameData": {
                "path": "DJXZ_IMG_DaoJuTuBiao.jpg",
                "plistFile": "DJXZ.plist",
                "resourceType": 1
              },
              "scale9Enable": false,
              "scale9Height": 70,
              "scale9Width": 77
            }
          },
          {
            "classname": "Label",
            "name": null,
            "children": [],
            "options": {
              "__type": "LabelSurrogate:#EditorCommon.JsonModel.Component.GUI",
              "classname": "Label",
              "name": "Label_daojumingcheng",
              "ZOrder": 0,
              "actiontag": 58635765,
              "anchorPointX": 0.5,
              "anchorPointY": 0.5,
              "classType": "CocoStudio.EngineAdapterWrap.CSLabel",
              "colorB": 255,
              "colorG": 255,
              "colorR": 255,
              "customProperty": "",
              "flipX": false,
              "flipY": false,
              "height": 27,
              "ignoreSize": true,
              "layoutParameter": null,
              "opacity": 255,
              "positionPercentX": -0.006535948,
              "positionPercentY": 0.385416657,
              "positionType": 0,
              "rotation": 0,
              "scaleX": 1,
              "scaleY": 1,
              "sizePercentX": 0.522875845,
              "sizePercentY": 0.140625,
              "sizeType": 0,
              "tag": 100,
              "touchAble": false,
              "useMergedTexture": false,
              "visible": true,
              "width": 80,
              "x": -1,
              "y": 74,
              "areaHeight": 0,
              "areaWidth": 0,
              "fontFile": null,
              "fontName": "微软雅黑",
              "fontSize": 20,
              "hAlignment": 0,
              "text": "道具名称",
              "touchScaleEnable": false,
              "vAlignment": 0
            }
          },
          {
            "classname": "Label",
            "name": null,
            "children": [],
            "options": {
              "__type": "LabelSurrogate:#EditorCommon.JsonModel.Component.GUI",
              "classname": "Label",
              "name": "Label_jinbishuliang",
              "ZOrder": 0,
              "actiontag": 64235341,
              "anchorPointX": 0.5,
              "anchorPointY": 0.5,
              "classType": "CocoStudio.EngineAdapterWrap.CSLabel",
              "colorB": 255,
              "colorG": 255,
              "colorR": 255,
              "customProperty": "",
              "flipX": false,
              "flipY": false,
              "height": 27,
              "ignoreSize": true,
              "layoutParameter": null,
              "opacity": 255,
              "positionPercentX": -0.045751635,
              "positionPercentY": -0.375,
              "positionType": 0,
              "rotation": 0,
              "scaleX": 1,
              "scaleY": 1,
              "sizePercentX": 0.3137255,
              "sizePercentY": 0.140625,
              "sizeType": 0,
              "tag": 101,
              "touchAble": false,
              "useMergedTexture": false,
              "visible": true,
              "width": 48,
              "x": -7,
              "y": -72,
              "areaHeight": 0,
              "areaWidth": 0,
              "fontFile": null,
              "fontName": "微软雅黑",
              "fontSize": 20,
              "hAlignment": 0,
              "text": "8888",
              "touchScaleEnable": false,
              "vAlignment": 0
            }
          },
          {
            "classname": "CheckBox",
            "name": null,
            "children": [],
            "options": {
              "__type": "CheckBoxSurrogate:#EditorCommon.JsonModel.Component.GUI",
              "classname": "CheckBox",
              "name": "CheckBox_daojuxuanze",
              "ZOrder": 0,
              "actiontag": 41247165,
              "anchorPointX": 0.5,
              "anchorPointY": 0.5,
              "classType": "CocoStudio.EngineAdapterWrap.CSCheckBox",
              "colorB": 255,
              "colorG": 255,
              "colorR": 255,
              "customProperty": "",
              "flipX": false,
              "flipY": false,
              "height": 61,
              "ignoreSize": true,
              "layoutParameter": null,
              "opacity": 255,
              "positionPercentX": 0.3398693,
              "positionPercentY": -0.40625,
              "positionType": 0,
              "rotation": 0,
              "scaleX": 1,
              "scaleY": 1,
              "sizePercentX": 0.405228764,
              "sizePercentY": 0.317708343,
              "sizeType": 0,
              "tag": 102,
              "touchAble": true,
              "useMergedTexture": false,
              "visible": true,
              "width": 62,
              "x": 52,
              "y": -78,
              "backGroundBox": null,
              "backGroundBoxData": {
                "path": "IMG_duigou.png",
                "plistFile": "DJXZ.plist",
                "resourceType": 1
              },
              "backGroundBoxDisabled": null,
              "backGroundBoxDisabledData": {
                "path": null,
                "plistFile": null,
                "resourceType": 0
              },
              "backGroundBoxSelected": null,
              "backGroundBoxSelectedData": {
                "path": null,
                "plistFile": null,
                "resourceType": 0
              },
              "frontCross": null,
              "frontCrossData": {
                "path": "IMG_duigou.png",
                "plistFile": "DJXZ.plist",
                "resourceType": 1
              },
              "frontCrossDisabled": null,
              "frontCrossDisabledData": {
                "path": null,
                "plistFile": null,
                "resourceType": 0
              },
              "selectedState": true
            }
          }
        ],
        "options": {
          "__type": "ButtonSurrogate:#EditorCommon.JsonModel.Component.GUI",
          "classname": "Button",
          "name": "Button_daoju",
          "ZOrder": 0,
          "actiontag": 27144664,
          "anchorPointX": 0.5,
          "anchorPointY": 0.5,
          "classType": "CocoStudio.EngineAdapterWrap.CSButton",
          "colorB": 255,
          "colorG": 255,
          "colorR": 255,
          "customProperty": "",
          "flipX": false,
          "flipY": false,
          "height": 192,
          "ignoreSize": true,
          "layoutParameter": null,
          "opacity": 255,
          "positionPercentX": 0.497142851,
          "positionPercentY": 0.4904762,
          "positionType": 0,
          "rotation": 0,
          "scaleX": 1,
          "scaleY": 1,
          "sizePercentX": 0.8742857,
          "sizePercentY": 0.9142857,
          "sizeType": 0,
          "tag": 98,
          "touchAble": true,
          "useMergedTexture": false,
          "visible": true,
          "width": 153,
          "x": 87,
          "y": 103,
          "capInsetsHeight": 1,
          "capInsetsWidth": 1,
          "capInsetsX": 0,
          "capInsetsY": 0,
          "disabled": null,
          "disabledData": {
            "path": "DJXZ_BN_DaoJuKuang.jpg",
            "plistFile": "DJXZ.plist",
            "resourceType": 1
          },
          "fontName": "微软雅黑",
          "fontSize": 14,
          "fontType": 0,
          "normal": null,
          "normalData": {
            "path": "DJXZ_BN_DaoJuKuang.jpg",
            "plistFile": "DJXZ.plist",
            "resourceType": 1
          },
          "pressed": null,
          "pressedData": {
            "path": "DJXZ_BN_DaoJuKuang.jpg",
            "plistFile": "DJXZ.plist",
            "resourceType": 1
          },
          "scale9Enable": false,
          "scale9Height": 192,
          "scale9Width": 153,
          "text": "",
          "textColorB": 255,
          "textColorG": 255,
          "textColorR": 255
        }
      }
    ],
    "options": {
      "__type": "PanelSurrogate:#EditorCommon.JsonModel.Component.GUI",
      "classname": "Panel",
      "name": "Panel_DJ",
      "ZOrder": 0,
      "actiontag": -1,
      "anchorPointX": 0,
      "anchorPointY": 0,
      "classType": "CocoStudio.EngineAdapterWrap.CSPanel",
      "colorB": 255,
      "colorG": 255,
      "colorR": 255,
      "customProperty": "",
      "flipX": false,
      "flipY": false,
      "height": 210,
      "ignoreSize": false,
      "layoutParameter": null,
      "opacity": 255,
      "positionPercentX": 0,
      "positionPercentY": 0,
      "positionType": 0,
      "rotation": 0,
      "scaleX": 1,
      "scaleY": 1,
      "sizePercentX": 1,
      "sizePercentY": 1,
      "sizeType": 0,
      "tag": 92,
      "touchAble": true,
      "useMergedTexture": false,
      "visible": true,
      "width": 175,
      "x": 0,
      "y": 0,
      "adaptScreen": false,
      "backGroundImage": null,
      "backGroundImageData": null,
      "backGroundScale9Enable": false,
      "bgColorB": 255,
      "bgColorG": 200,
      "bgColorOpacity": 0,
      "bgColorR": 150,
      "bgEndColorB": 255,
      "bgEndColorG": 200,
      "bgEndColorR": 150,
      "bgStartColorB": 255,
      "bgStartColorG": 255,
      "bgStartColorR": 255,
      "capInsetsHeight": 1,
      "capInsetsWidth": 1,
      "capInsetsX": 0,
      "capInsetsY": 0,
      "clipAble": false,
      "colorType": 1,
      "layoutType": 0,
      "vectorX": 0,
      "vectorY": -0.5
    }
  }
}