{
  "classname": null,
  "name": null,
  "animation": {
    "classname": null,
    "name": "AnimationManager",
    "actionlist": []
  },
  "dataScale": 1,
  "designHeight": 98,
  "designWidth": 543,
  "textures": [],
  "texturesPng": [],
  "version": "1.6.0.0",
  "widgetTree": {
    "classname": "Panel",
    "name": null,
    "children": [
      {
        "classname": "ImageView",
        "name": null,
        "children": [
          {
            "classname": "Panel",
            "name": null,
            "children": [
              {
                "classname": "ImageView",
                "name": null,
                "children": [
                  {
                    "classname": "ImageView",
                    "name": null,
                    "children": [],
                    "options": {
                      "__type": "ImageViewSurrogate:#EditorCommon.JsonModel.Component.GUI",
                      "classname": "ImageView",
                      "name": "Image_touxiang",
                      "ZOrder": 0,
                      "actiontag": 63726012,
                      "anchorPointX": 0.5,
                      "anchorPointY": 0.5,
                      "classType": "CocoStudio.EngineAdapterWrap.CSImageView",
                      "colorB": 255,
                      "colorG": 255,
                      "colorR": 255,
                      "customProperty": "",
                      "flipX": false,
                      "flipY": false,
                      "height": 75,
                      "ignoreSize": true,
                      "layoutParameter": null,
                      "opacity": 255,
                      "positionPercentX": 0,
                      "positionPercentY": 0.0133333337,
                      "positionType": 0,
                      "rotation": 0,
                      "scaleX": 1,
                      "scaleY": 1,
                      "sizePercentX": 1,
                      "sizePercentY": 1,
                      "sizeType": 0,
                      "tag": 234,
                      "touchAble": false,
                      "useMergedTexture": false,
                      "visible": true,
                      "width": 75,
                      "x": 0,
                      "y": 1,
                      "capInsetsHeight": 1,
                      "capInsetsWidth": 1,
                      "capInsetsX": 0,
                      "capInsetsY": 0,
                      "fileName": null,
                      "fileNameData": {
                        "path": "IMG_Main_Photo.png",
                        "plistFile": "GGZY_PNG/GGZY.plist",
                        "resourceType": 1
                      },
                      "scale9Enable": false,
                      "scale9Height": 75,
                      "scale9Width": 75
                    }
                  }
                ],
                "options": {
                  "__type": "ImageViewSurrogate:#EditorCommon.JsonModel.Component.GUI",
                  "classname": "ImageView",
                  "name": "Image_touxiang_ditu",
                  "ZOrder": 0,
                  "actiontag": 41592157,
                  "anchorPointX": 0.5,
                  "anchorPointY": 0.5,
                  "classType": "CocoStudio.EngineAdapterWrap.CSImageView",
                  "colorB": 255,
                  "colorG": 255,
                  "colorR": 255,
                  "customProperty": "",
                  "flipX": false,
                  "flipY": false,
                  "height": 75,
                  "ignoreSize": true,
                  "layoutParameter": null,
                  "opacity": 255,
                  "positionPercentX": 0.49333334,
                  "positionPercentY": 0.48,
                  "positionType": 0,
                  "rotation": 0,
                  "scaleX": 1,
                  "scaleY": 1,
                  "sizePercentX": 1,
                  "sizePercentY": 1,
                  "sizeType": 0,
                  "tag": 65,
                  "touchAble": false,
                  "useMergedTexture": false,
                  "visible": true,
                  "width": 75,
                  "x": 37,
                  "y": 36,
                  "capInsetsHeight": 1,
                  "capInsetsWidth": 1,
                  "capInsetsX": 0,
                  "capInsetsY": 0,
                  "fileName": null,
                  "fileNameData": {
                    "path": "IMG_Main_Photo.png",
                    "plistFile": "GGZY_PNG/GGZY.plist",
                    "resourceType": 1
                  },
                  "scale9Enable": false,
                  "scale9Height": 75,
                  "scale9Width": 75
                }
              }
            ],
            "options": {
              "__type": "PanelSurrogate:#EditorCommon.JsonModel.Component.GUI",
              "classname": "Panel",
              "name": "Panel_9",
              "ZOrder": 0,
              "actiontag": 25833645,
              "anchorPointX": 0,
              "anchorPointY": 0,
              "classType": "CocoStudio.EngineAdapterWrap.CSPanel",
              "colorB": 255,
              "colorG": 255,
              "colorR": 255,
              "customProperty": "",
              "flipX": false,
              "flipY": false,
              "height": 75,
              "ignoreSize": false,
              "layoutParameter": null,
              "opacity": 255,
              "positionPercentX": -0.453038663,
              "positionPercentY": -0.367346942,
              "positionType": 0,
              "rotation": 0,
              "scaleX": 1,
              "scaleY": 1,
              "sizePercentX": 0.138121545,
              "sizePercentY": 0.7653061,
              "sizeType": 0,
              "tag": 373,
              "touchAble": false,
              "useMergedTexture": false,
              "visible": true,
              "width": 75,
              "x": -246,
              "y": -36,
              "adaptScreen": false,
              "backGroundImage": null,
              "backGroundImageData": null,
              "backGroundScale9Enable": false,
              "bgColorB": 255,
              "bgColorG": 200,
              "bgColorOpacity": 100,
              "bgColorR": 150,
              "bgEndColorB": 255,
              "bgEndColorG": 200,
              "bgEndColorR": 150,
              "bgStartColorB": 255,
              "bgStartColorG": 255,
              "bgStartColorR": 255,
              "capInsetsHeight": 1,
              "capInsetsWidth": 1,
              "capInsetsX": 0,
              "capInsetsY": 0,
              "clipAble": true,
              "colorType": 1,
              "layoutType": 0,
              "vectorX": 0,
              "vectorY": -0.5
            }
          },
          {
            "classname": "Label",
            "name": null,
            "children": [],
            "options": {
              "__type": "LabelSurrogate:#EditorCommon.JsonModel.Component.GUI",
              "classname": "Label",
              "name": "Label_nicheng",
              "ZOrder": 0,
              "actiontag": 30997993,
              "anchorPointX": 0,
              "anchorPointY": 0,
              "classType": "CocoStudio.EngineAdapterWrap.CSLabel",
              "colorB": 0,
              "colorG": 0,
              "colorR": 0,
              "customProperty": "",
              "flipX": false,
              "flipY": false,
              "height": 24,
              "ignoreSize": true,
              "layoutParameter": null,
              "opacity": 255,
              "positionPercentX": -0.246777162,
              "positionPercentY": 0.20408164,
              "positionType": 0,
              "rotation": 0,
              "scaleX": 1,
              "scaleY": 1,
              "sizePercentX": 0.198895022,
              "sizePercentY": 0.244897962,
              "sizeType": 0,
              "tag": 66,
              "touchAble": false,
              "useMergedTexture": false,
              "visible": true,
              "width": 108,
              "x": -134,
              "y": 20,
              "areaHeight": 0,
              "areaWidth": 0,
              "fontFile": null,
              "fontName": "微软雅黑",
              "fontSize": 18,
              "hAlignment": 0,
              "text": "昵称不拉不拉",
              "touchScaleEnable": false,
              "vAlignment": 0
            }
          },
          {
            "classname": "Label",
            "name": null,
            "children": [],
            "options": {
              "__type": "LabelSurrogate:#EditorCommon.JsonModel.Component.GUI",
              "classname": "Label",
              "name": "Label_renqi",
              "ZOrder": 0,
              "actiontag": 42521733,
              "anchorPointX": 1.49011612E-08,
              "anchorPointY": 0.5,
              "classType": "CocoStudio.EngineAdapterWrap.CSLabel",
              "colorB": 127,
              "colorG": 64,
              "colorR": 0,
              "customProperty": "",
              "flipX": false,
              "flipY": false,
              "height": 32,
              "ignoreSize": true,
              "layoutParameter": null,
              "opacity": 255,
              "positionPercentX": -0.246777162,
              "positionPercentY": 0.0306122452,
              "positionType": 0,
              "rotation": 0,
              "scaleX": 1,
              "scaleY": 1,
              "sizePercentX": 0.09208103,
              "sizePercentY": 0.3265306,
              "sizeType": 0,
              "tag": 68,
              "touchAble": false,
              "useMergedTexture": false,
              "visible": true,
              "width": 50,
              "x": -134,
              "y": 3,
              "areaHeight": 0,
              "areaWidth": 0,
              "fontFile": null,
              "fontName": "微软雅黑",
              "fontSize": 25,
              "hAlignment": 0,
              "text": "人气",
              "touchScaleEnable": false,
              "vAlignment": 0
            }
          },
          {
            "classname": "Label",
            "name": null,
            "children": [],
            "options": {
              "__type": "LabelSurrogate:#EditorCommon.JsonModel.Component.GUI",
              "classname": "Label",
              "name": "Label_szrq_shuzi",
              "ZOrder": 0,
              "actiontag": 20600319,
              "anchorPointX": 0,
              "anchorPointY": 0,
              "classType": "CocoStudio.EngineAdapterWrap.CSLabel",
              "colorB": 0,
              "colorG": 0,
              "colorR": 0,
              "customProperty": "",
              "flipX": false,
              "flipY": false,
              "height": 24,
              "ignoreSize": true,
              "layoutParameter": null,
              "opacity": 255,
              "positionPercentX": -0.2946593,
              "positionPercentY": -0.408163279,
              "positionType": 0,
              "rotation": 0,
              "scaleX": 1,
              "scaleY": 1,
              "sizePercentX": 0.0202578269,
              "sizePercentY": 0.244897962,
              "sizeType": 0,
              "tag": 72,
              "touchAble": false,
              "useMergedTexture": false,
              "visible": true,
              "width": 11,
              "x": -160,
              "y": -40,
              "areaHeight": 0,
              "areaWidth": 0,
              "fontFile": null,
              "fontName": "微软雅黑",
              "fontSize": 18,
              "hAlignment": 0,
              "text": "0",
              "touchScaleEnable": false,
              "vAlignment": 0
            }
          },
          {
            "classname": "ImageView",
            "name": null,
            "children": [],
            "options": {
              "__type": "ImageViewSurrogate:#EditorCommon.JsonModel.Component.GUI",
              "classname": "ImageView",
              "name": "Image_xingbie",
              "ZOrder": 0,
              "actiontag": 49946031,
              "anchorPointX": 0.5,
              "anchorPointY": 0.5,
              "classType": "CocoStudio.EngineAdapterWrap.CSImageView",
              "colorB": 255,
              "colorG": 255,
              "colorR": 255,
              "customProperty": "",
              "flipX": false,
              "flipY": false,
              "height": 21,
              "ignoreSize": true,
              "layoutParameter": null,
              "opacity": 255,
              "positionPercentX": -0.272559851,
              "positionPercentY": 0.316326529,
              "positionType": 0,
              "rotation": 0,
              "scaleX": 1,
              "scaleY": 1,
              "sizePercentX": 0.0405156538,
              "sizePercentY": 0.214285716,
              "sizeType": 0,
              "tag": 211,
              "touchAble": false,
              "useMergedTexture": false,
              "visible": true,
              "width": 22,
              "x": -148,
              "y": 31,
              "capInsetsHeight": 1,
              "capInsetsWidth": 1,
              "capInsetsX": 0,
              "capInsetsY": 0,
              "fileName": null,
              "fileNameData": {
                "path": "IMG_Blue_Boy.png",
                "plistFile": "GGZY_PNG/GGZY.plist",
                "resourceType": 1
              },
              "scale9Enable": false,
              "scale9Height": 21,
              "scale9Width": 22
            }
          },
          {
            "classname": "LabelAtlas",
            "name": null,
            "children": [],
            "options": {
              "__type": "LabelAtlasSurrogate:#EditorCommon.JsonModel.Component.GUI",
              "classname": "LabelAtlas",
              "name": "AtlasLabel_renqi_shuzi",
              "ZOrder": 0,
              "actiontag": 61820044,
              "anchorPointX": 1.49011612E-08,
              "anchorPointY": 0.5,
              "classType": "CocoStudio.EngineAdapterWrap.CSLabelAtlas",
              "colorB": 255,
              "colorG": 255,
              "colorR": 255,
              "customProperty": "",
              "flipX": false,
              "flipY": false,
              "height": 31,
              "ignoreSize": true,
              "layoutParameter": null,
              "opacity": 255,
              "positionPercentX": -0.3020258,
              "positionPercentY": -0.0102040814,
              "positionType": 0,
              "rotation": 0,
              "scaleX": 1,
              "scaleY": 1,
              "sizePercentX": 0.03683241,
              "sizePercentY": 0.316326529,
              "sizeType": 0,
              "tag": 212,
              "touchAble": false,
              "useMergedTexture": false,
              "visible": true,
              "width": 20,
              "x": -164,
              "y": -1,
              "charMapFile": null,
              "charMapFileData": {
                "path": "GGZY_PNG/IMG_Number_Blue.png",
                "plistFile": "",
                "resourceType": 0
              },
              "itemHeight": 31,
              "itemWidth": 20,
              "startCharMap": "0",
              "stringValue": "0"
            }
          },
          {
            "classname": "ImageView",
            "name": null,
            "children": [],
            "options": {
              "__type": "ImageViewSurrogate:#EditorCommon.JsonModel.Component.GUI",
              "classname": "ImageView",
              "name": "Image_tebieguanzhu",
              "ZOrder": 0,
              "actiontag": 19810832,
              "anchorPointX": 0.5,
              "anchorPointY": 0.5,
              "classType": "CocoStudio.EngineAdapterWrap.CSImageView",
              "colorB": 255,
              "colorG": 255,
              "colorR": 255,
              "customProperty": "",
              "flipX": false,
              "flipY": false,
              "height": 32,
              "ignoreSize": true,
              "layoutParameter": null,
              "opacity": 255,
              "positionPercentX": 0.1694291,
              "positionPercentY": 0.0102040814,
              "positionType": 0,
              "rotation": 0,
              "scaleX": 1,
              "scaleY": 1,
              "sizePercentX": 0.05893186,
              "sizePercentY": 0.3265306,
              "sizeType": 0,
              "tag": 213,
              "touchAble": false,
              "useMergedTexture": false,
              "visible": true,
              "width": 32,
              "x": 92,
              "y": 1,
              "capInsetsHeight": 1,
              "capInsetsWidth": 1,
              "capInsetsX": 0,
              "capInsetsY": 0,
              "fileName": null,
              "fileNameData": {
                "path": "BTN_Number_Add_1.png",
                "plistFile": "GGZY_PNG/GGZY.plist",
                "resourceType": 1
              },
              "scale9Enable": false,
              "scale9Height": 32,
              "scale9Width": 32
            }
          },
          {
            "classname": "ImageView",
            "name": null,
            "children": [],
            "options": {
              "__type": "ImageViewSurrogate:#EditorCommon.JsonModel.Component.GUI",
              "classname": "ImageView",
              "name": "Image_haoyou",
              "ZOrder": 0,
              "actiontag": 10305078,
              "anchorPointX": 0.5,
              "anchorPointY": 0.5,
              "classType": "CocoStudio.EngineAdapterWrap.CSImageView",
              "colorB": 255,
              "colorG": 255,
              "colorR": 255,
              "customProperty": "",
              "flipX": false,
              "flipY": false,
              "height": 32,
              "ignoreSize": true,
              "layoutParameter": null,
              "opacity": 255,
              "positionPercentX": 0.3499079,
              "positionPercentY": 0.0204081628,
              "positionType": 0,
              "rotation": 0,
              "scaleX": 1,
              "scaleY": 1,
              "sizePercentX": 0.05893186,
              "sizePercentY": 0.3265306,
              "sizeType": 0,
              "tag": 214,
              "touchAble": false,
              "useMergedTexture": false,
              "visible": true,
              "width": 32,
              "x": 190,
              "y": 2,
              "capInsetsHeight": 1,
              "capInsetsWidth": 1,
              "capInsetsX": 0,
              "capInsetsY": 0,
              "fileName": null,
              "fileNameData": {
                "path": "BTN_Number_Add_1.png",
                "plistFile": "GGZY_PNG/GGZY.plist",
                "resourceType": 1
              },
              "scale9Enable": false,
              "scale9Height": 32,
              "scale9Width": 32
            }
          }
        ],
        "options": {
          "__type": "ImageViewSurrogate:#EditorCommon.JsonModel.Component.GUI",
          "classname": "ImageView",
          "name": "Image_tpxx_beijing",
          "ZOrder": 0,
          "actiontag": 62629777,
          "anchorPointX": 0.5,
          "anchorPointY": 0.5,
          "classType": "CocoStudio.EngineAdapterWrap.CSImageView",
          "colorB": 255,
          "colorG": 255,
          "colorR": 255,
          "customProperty": "",
          "flipX": false,
          "flipY": false,
          "height": 98,
          "ignoreSize": true,
          "layoutParameter": null,
          "opacity": 255,
          "positionPercentX": 0.5174954,
          "positionPercentY": 0.489795923,
          "positionType": 0,
          "rotation": 0,
          "scaleX": 1,
          "scaleY": 1,
          "sizePercentX": 1,
          "sizePercentY": 1,
          "sizeType": 0,
          "tag": 62,
          "touchAble": false,
          "useMergedTexture": false,
          "visible": true,
          "width": 543,
          "x": 281,
          "y": 48,
          "capInsetsHeight": 1,
          "capInsetsWidth": 1,
          "capInsetsX": 0,
          "capInsetsY": 0,
          "fileName": null,
          "fileNameData": {
            "path": "IMG_Info_Others_Bg.png",
            "plistFile": "GGZY_PNG/GGZY.plist",
            "resourceType": 1
          },
          "scale9Enable": false,
          "scale9Height": 98,
          "scale9Width": 543
        }
      }
    ],
    "options": {
      "__type": "PanelSurrogate:#EditorCommon.JsonModel.Component.GUI",
      "classname": "Panel",
      "name": "Panel_TPXX",
      "ZOrder": 0,
      "actiontag": -1,
      "anchorPointX": 0,
      "anchorPointY": 0,
      "classType": "CocoStudio.EngineAdapterWrap.CSPanel",
      "colorB": 255,
      "colorG": 255,
      "colorR": 255,
      "customProperty": "",
      "flipX": false,
      "flipY": false,
      "height": 98,
      "ignoreSize": false,
      "layoutParameter": null,
      "opacity": 255,
      "positionPercentX": 0,
      "positionPercentY": 0,
      "positionType": 0,
      "rotation": 0,
      "scaleX": 1,
      "scaleY": 1,
      "sizePercentX": 1,
      "sizePercentY": 1,
      "sizeType": 0,
      "tag": 61,
      "touchAble": false,
      "useMergedTexture": false,
      "visible": true,
      "width": 543,
      "x": 0,
      "y": 0,
      "adaptScreen": false,
      "backGroundImage": null,
      "backGroundImageData": null,
      "backGroundScale9Enable": false,
      "bgColorB": 255,
      "bgColorG": 200,
      "bgColorOpacity": 0,
      "bgColorR": 150,
      "bgEndColorB": 255,
      "bgEndColorG": 200,
      "bgEndColorR": 150,
      "bgStartColorB": 255,
      "bgStartColorG": 255,
      "bgStartColorR": 255,
      "capInsetsHeight": 1,
      "capInsetsWidth": 1,
      "capInsetsX": 0,
      "capInsetsY": 0,
      "clipAble": false,
      "colorType": 1,
      "layoutType": 0,
      "vectorX": 0,
      "vectorY": -0.5
    }
  }
}